pptestwojtekmacias/__init__.py
pptestwojtekmacias/mmodpptest.py
pptestwojtekmacias-0.0.1.dist-info/LICENCE.txt
pptestwojtekmacias-0.0.1.dist-info/METADATA
pptestwojtekmacias-0.0.1.dist-info/WHEEL
pptestwojtekmacias-0.0.1.dist-info/top_level.txt
pptestwojtekmacias-0.0.1.dist-info/RECORD
