Metadata-Version: 2.1
Name: pptestwojtekmacias
Version: 0.0.1
Summary: My test package
Author-email: AZ <wojt.macias@gmail.com>
License: MIT License
Keywords: pptestwojtekmacias,funny funkcjons,name,surname,personal data
Classifier: Environment :: Console :: Newt
Requires-Python: >=3.0
License-File: LICENCE.txt
Requires-Dist: numpy ; python_version >= "3.0"
